unifactory/__init__.py
unifactory-0.1.0.dist-info/LICENSE
unifactory-0.1.0.dist-info/METADATA
unifactory-0.1.0.dist-info/WHEEL
unifactory-0.1.0.dist-info/RECORD
