Metadata-Version: 2.1
Name: unifactory
Version: 0.1.0
Summary: Automatically choose the right polyfactory.
Home-page: https://github.com/phha/unifactory
License: MIT
Keywords: polyfactory
Author: Philipp Hack
Author-email: philipp.hack@gmail.com
Requires-Python: >=3.10,<4.0
Classifier: License :: OSI Approved :: MIT License
Classifier: Programming Language :: Python :: 3
Classifier: Programming Language :: Python :: 3.10
Classifier: Programming Language :: Python :: 3.11
Classifier: Programming Language :: Python :: 3.12
Requires-Dist: polyfactory (>=2.13.0,<3.0.0)
Project-URL: Repository, https://github.com/phha/unifactory
